pagepilotft/PagePilot.py
pagepilotft/core/PilotMiddleware.py
pagepilotft/core/PilotParams.py
pagepilotft/core/PilotState.py
pagepilotft/core/PilotView.py
pagepilotft/core/__init__.py
pagepilotft/views/InternalErrorView.py
pagepilotft/views/NotFoundView.py
pagepilotft/views/__init__.py
pagepilotft-0.1.0.dist-info/METADATA
pagepilotft-0.1.0.dist-info/WHEEL
pagepilotft-0.1.0.dist-info/top_level.txt
pagepilotft-0.1.0.dist-info/RECORD
