Metadata-Version: 2.4
Name: pagepilotft
Version: 0.1.0
Summary: Dynamic path library for Flet apps
Author-email: Héctor <danielramirezr27@gmail.com>
License: MIT
Keywords: testing,logging,example
Classifier: Programming Language :: Python :: 3
Classifier: License :: OSI Approved :: MIT License
Classifier: Operating System :: OS Independent
Requires-Python: >=3.6
Requires-Dist: flet>=0.27.6
Requires-Dist: repath>=0.1.2
